tenzir_test/__init__.py
tenzir_test/_python_runner.py
tenzir_test/cli.py
tenzir_test/config.py
tenzir_test/packages.py
tenzir_test/py.typed
tenzir_test/run.py
tenzir_test/engine/__init__.py
tenzir_test/engine/operations.py
tenzir_test/engine/registry.py
tenzir_test/engine/state.py
tenzir_test/engine/worker.py
tenzir_test/fixtures/__init__.py
tenzir_test/fixtures/node.py
tenzir_test/runners/__init__.py
tenzir_test/runners/_utils.py
tenzir_test/runners/custom_python_fixture_runner.py
tenzir_test/runners/diff_runner.py
tenzir_test/runners/ext_runner.py
tenzir_test/runners/runner.py
tenzir_test/runners/shell_runner.py
tenzir_test/runners/tenzir_runner.py
tenzir_test/runners/tql_runner.py
tenzir_test-1.1.0.dist-info/METADATA
tenzir_test-1.1.0.dist-info/WHEEL
tenzir_test-1.1.0.dist-info/entry_points.txt
tenzir_test-1.1.0.dist-info/licenses/LICENSE
tenzir_test-1.1.0.dist-info/RECORD
