Metadata-Version: 2.4
Name: tenzir-test
Version: 1.1.0
Summary: Reusable test execution framework extracted from the Tenzir repository.
Project-URL: Homepage, https://github.com/tenzir/test
Project-URL: Repository, https://github.com/tenzir/test
Project-URL: Bug Tracker, https://github.com/tenzir/test/issues
Project-URL: Documentation, https://docs.tenzir.com
Author-email: Tenzir <engineering@tenzir.com>
Maintainer-email: Tenzir Engineering <engineering@tenzir.com>
License: Apache-2.0
License-File: LICENSE
Keywords: automation,pytest,tenzir,testing
Classifier: Development Status :: 4 - Beta
Classifier: Intended Audience :: Developers
Classifier: License :: OSI Approved :: Apache Software License
Classifier: Operating System :: OS Independent
Classifier: Programming Language :: Python :: 3
Classifier: Programming Language :: Python :: 3.12
Classifier: Programming Language :: Python :: 3.13
Classifier: Topic :: Software Development :: Libraries :: Python Modules
Classifier: Topic :: Software Development :: Quality Assurance
Classifier: Topic :: Software Development :: Testing
Classifier: Typing :: Typed
Requires-Python: >=3.12
Requires-Dist: click>=8.1
Requires-Dist: pyyaml>=6.0
